superfork/__init__.py
superfork/fork.py
superfork/utils.py
superfork-0.0.4.dist-info/LICENSE
superfork-0.0.4.dist-info/METADATA
superfork-0.0.4.dist-info/WHEEL
superfork-0.0.4.dist-info/entry_points.txt
superfork-0.0.4.dist-info/top_level.txt
superfork-0.0.4.dist-info/RECORD
