Metadata-Version: 2.2
Name: superfork
Version: 0.0.4
Summary: Fork or sync a repo, or clone a user or org on GitHub to GitHub
Author-email: Will Fitzgerald <will.fitzgerald@pobox.com>
Project-URL: Homepage, https://willf.github.io/superfork/
Project-URL: Repository, https://github.com/willf/superfork
Project-URL: Documentation, https://willf.github.io/superfork/
Keywords: python
Classifier: Intended Audience :: Developers
Classifier: Programming Language :: Python
Classifier: Programming Language :: Python :: 3
Classifier: Programming Language :: Python :: 3.11
Classifier: Programming Language :: Python :: 3.12
Classifier: Programming Language :: Python :: 3.13
Classifier: Topic :: Software Development :: Libraries :: Python Modules
Requires-Python: <4.0,>=3.11
License-File: LICENSE
Requires-Dist: click>=8.1.8
Requires-Dist: pygithub>=2.5.0
Requires-Dist: python-dotenv>=1.0.1
Requires-Dist: rich>=13.9.4
